displayforecastio
tests
