Metadata-Version: 1.0
Name: displayforecastio
Version: 1.2
Summary: Display the current weather in your terminal
Home-page: https://github.com/Bachmann1234/displayforecastio
Author: Matt Bachmann
Author-email: UNKNOWN
License: Apache 2.0
Platform: UNKNOWN
